[
  {
      "status": "OPEN",
      "startingAirport": "608f18072621d540f80dee61",
      "destinationAirport": "608f18072621d540f80dee62",
      "startingDate": "2021-05-10T16:00:00Z",
      "tickets": [
          {
              "status": "OPEN",
              "price": {
                  "value": 100,
                  "currency": "PLN"
              },
              "class": "ECONOMY",
              "airplanePosition": "EC01"
          },
          {
              "status": "OPEN",
              "price": {
                  "value": 100,
                  "currency": "PLN"
              },
              "class": "ECONOMY",
              "airplanePosition": "EC02"
          },
          {
              "status": "OPEN",
              "price": {
                  "value": 100,
                  "currency": "PLN"
              },
              "class": "ECONOMY",
              "airplanePosition": "EC03"
          },
          {
              "status": "OPEN",
              "price": {
                  "value": 150,
                  "currency": "PLN"
              },
              "class": "STANDARD",
              "airplanePosition": "ST01"
          },
          {
              "status": "OPEN",
              "price": {
                  "value": 150,
                  "currency": "PLN"
              },
              "class": "STANDARD",
              "airplanePosition": "ST02"
          },
          {
              "status": "CLOSED",
              "price": {
                  "value": 150,
                  "currency": "PLN"
              },
              "class": "STANDARD",
              "airplanePosition": "ST03"
          },
          {
              "status": "CLOSED",
              "price": {
                  "value": 150,
                  "currency": "PLN"
              },
              "class": "STANDARD",
              "airplanePosition": "ST04"
          },
          {
              "status": "OPEN",
              "price": {
                  "value": 250,
                  "currency": "PLN"
              },
              "class": "PREMIUM",
              "airplanePosition": "PR01"
          },
          {
              "status": "OPEN",
              "price": {
                  "value": 252,
                  "currency": "PLN"
              },
              "class": "PREMIUM",
              "airplanePosition": "PR02"
          },
          {
              "status": "CLOSED",
              "price": {
                  "value": 250,
                  "currency": "PLN"
              },
              "class": "PREMIUM",
              "airplanePosition": "PR03"
          }
      ],
      "estimatedFlightTime": 240
  },
  {
      "status": "OPEN",
      "startingAirport": "608f18072621d540f80dee61",
      "destinationAirport": "608f18072621d540f80dee63",
      "startingDate": "2021-05-15T20:00:00Z",
      "tickets": [
          {
              "status": "OPEN",
              "price": {
                  "value": 150,
                  "currency": "PLN"
              },
              "class": "ECONOMY",
              "airplanePosition": "EC01"
          },
          {
              "status": "OPEN",
              "price": {
                  "value": 150,
                  "currency": "PLN"
              },
              "class": "ECONOMY",
              "airplanePosition": "EC02"
          },
          {
              "status": "OPEN",
              "price": {
                  "value": 150,
                  "currency": "PLN"
              },
              "class": "ECONOMY",
              "airplanePosition": "EC03"
          },
          {
              "status": "OPEN",
              "price": {
                  "value": 225,
                  "currency": "PLN"
              },
              "class": "STANDARD",
              "airplanePosition": "ST01"
          },
          {
              "status": "OPEN",
              "price": {
                  "value": 225,
                  "currency": "PLN"
              },
              "class": "STANDARD",
              "airplanePosition": "ST02"
          },
          {
              "status": "CLOSED",
              "price": {
                  "value": 225,
                  "currency": "PLN"
              },
              "class": "STANDARD",
              "airplanePosition": "ST03"
          },
          {
              "status": "CLOSED",
              "price": {
                  "value": 225,
                  "currency": "PLN"
              },
              "class": "STANDARD",
              "airplanePosition": "ST04"
          },
          {
              "status": "OPEN",
              "price": {
                  "value": 350,
                  "currency": "PLN"
              },
              "class": "PREMIUM",
              "airplanePosition": "PR01"
          },
          {
              "status": "OPEN",
              "price": {
                  "value": 350,
                  "currency": "PLN"
              },
              "class": "PREMIUM",
              "airplanePosition": "PR02"
          },
          {
              "status": "CLOSED",
              "price": {
                  "value": 350,
                  "currency": "PLN"
              },
              "class": "PREMIUM",
              "airplanePosition": "PR03"
          }
      ],
      "estimatedFlightTime": 360
  },
  {
    "status": "OPEN",
    "startingAirport": "608f18072621d540f80dee61",
    "destinationAirport": "608f18072621d540f80dee64",
    "startingDate": "2021-05-20T20:00:00Z",
    "tickets": [
        {
            "status": "OPEN",
            "price": {
                "value": 185,
                "currency": "PLN"
            },
            "class": "ECONOMY",
            "airplanePosition": "EC01"
        },
        {
            "status": "OPEN",
            "price": {
                "value": 185,
                "currency": "PLN"
            },
            "class": "ECONOMY",
            "airplanePosition": "EC02"
        },
        {
            "status": "OPEN",
            "price": {
                "value": 185,
                "currency": "PLN"
            },
            "class": "ECONOMY",
            "airplanePosition": "EC03"
        },
        {
            "status": "OPEN",
            "price": {
                "value": 240,
                "currency": "PLN"
            },
            "class": "STANDARD",
            "airplanePosition": "ST01"
        },
        {
            "status": "OPEN",
            "price": {
                "value": 240,
                "currency": "PLN"
            },
            "class": "STANDARD",
            "airplanePosition": "ST02"
        },
        {
            "status": "CLOSED",
            "price": {
                "value": 225,
                "currency": "PLN"
            },
            "class": "STANDARD",
            "airplanePosition": "ST03"
        },
        {
            "status": "CLOSED",
            "price": {
                "value": 240,
                "currency": "PLN"
            },
            "class": "STANDARD",
            "airplanePosition": "ST04"
        },
        {
            "status": "OPEN",
            "price": {
                "value": 340,
                "currency": "PLN"
            },
            "class": "PREMIUM",
            "airplanePosition": "PR01"
        },
        {
            "status": "OPEN",
            "price": {
                "value": 340,
                "currency": "PLN"
            },
            "class": "PREMIUM",
            "airplanePosition": "PR02"
        },
        {
            "status": "CLOSED",
            "price": {
                "value": 340,
                "currency": "PLN"
            },
            "class": "PREMIUM",
            "airplanePosition": "PR03"
        }
    ],
    "estimatedFlightTime": 400
}
]